{
  "data": {
    "objects": {
      "summary_title": ["drawing"],
      "admin": {
        "id": ["object-7931"],
        "source": ["adlib"]
      },
      "URI": ["https://data.fitzmuseum.cam.ac.uk/id/object/7931"],
      "apiURI": ["https://data.fitzmuseum.cam.ac.uk/api/v1/objects/object-7931"],
      "id": ["object-7931"]
    },
    "admin": {
      "id": ["media-3528641786"]
    },
    "source": {
      "attributes": {
        "Copyright": [
          ["Photograph copyright © The Fitzwilliam Museum, Cambridge."]
        ],
        "Cataloged": [
          ["2018-09-17T03:26:40Z"]
        ],
        "Keywords": [
          ["18th Century"],
          ["_WF_AdOK"],
          ["_WF_KWD"],
          ["_WF_OPAC"],
          ["_WF_Recto"],
          ["architectural"],
          ["architecture"],
          ["barns"],
          ["drawing"],
          ["exterior"],
          ["farms"],
          ["farmyard"],
          ["Fitz_PDP"],
          ["Giovanni Battista Tiepolo"],
          ["Italian"],
          ["outbuildings"],
          ["recto"],
          ["sketch"],
          ["thatched"],
          ["Tiepolo"]
        ],
        "IPTC_-_Rights_Usage_Terms": [
          ["http://www.fitzmuseum.cam.ac.uk/aboutus/imagelibrary/termsandcondition"]
        ],
        "File_Description": [
          ["Recto: A thatched barn. Verso: A sketch for a figure with right arm raised (1); unidentified subject (2). Tiepolo, Giovanni Battista (Italian, 1696-1770).  Recto: pen, brown ink and wash verso: sketch (1): pen and brown ink; sketch (2): black chalk and brown wash on paper. Height 160 mm, width 257 mm. Production Note: Sketch verso in a similar posture to the Fitzwilliam drawing of the same subject (accession no. 2238)."]
        ]
      }
    },
    "apiURI": ["https://data.fitzmuseum.cam.ac.uk/api/v1/images/media-3528641786"],
    "uri": ["https://data.fitzmuseum.cam.ac.uk/id/image/media-3528641786"],
    "images": {
      "preview": {
        "resizable": [true],
        "format": ["jpeg"],
        "modified": [1537154800000],
        "location": ["https://data.fitzmuseum.cam.ac.uk/imagestore/portfolio/F25982D9_7CB9_CFFF_028E_8BBFC531887C/590/822/preview_PD_128_1961_recto_mas.jpg"],
        "location_is_relative": [true],
        "type": ["image"],
        "measurements": {
          "dimensions": [
            {
              "units": ["pixels"],
              "dimension": ["height"],
              "value": [188]
            },
            {
              "units": ["pixels"],
              "dimension": ["width"],
              "value": [250]
            }
          ]
        }
      },
      "original": {
        "processed": [true],
        "resizable": [true],
        "format": ["jpeg"],
        "modified": [1537154800000],
        "location": ["https://data.fitzmuseum.cam.ac.uk/imagestore/portfolio/F25982D9_7CB9_CFFF_028E_8BBFC531887C/590/822/PD_128_1961_recto_mas.jpg"],
        "location_is_relative": [true],
        "type": ["image"],
        "measurements": {
          "dimensions": [
            {
              "units": ["pixels"],
              "dimension": ["height"],
              "value": [4008]
            },
            {
              "units": ["pixels"],
              "dimension": ["width"],
              "value": [5344]
            }
          ]
        }
      },
      "large": {
        "resizable": [true],
        "format": ["jpeg"],
        "modified": [1537154800000],
        "location": ["https://data.fitzmuseum.cam.ac.uk/imagestore/portfolio/F25982D9_7CB9_CFFF_028E_8BBFC531887C/590/822/large_PD_128_1961_recto_mas.jpg"],
        "location_is_relative": [true],
        "type": ["image"],
        "measurements": {
          "dimensions": [
            {
              "units": ["pixels"],
              "dimension": ["height"],
              "value": [768]
            },
            {
              "units": ["pixels"],
              "dimension": ["width"],
              "value": [1024]
            }
          ]
        }
      },
      "zoom": {
        "resizable": [true],
        "format": ["pyramid tiff"],
        "modified": [1537154800000],
        "location": ["http://api.fitz.ms/iipsrv/iipsrv.fcgi?FIF=/portfolio/F25982D9_7CB9_CFFF_028E_8BBFC531887C/590/822/PD_128_1961_recto_mas.ptif&cvt=jpeg"],
        "location_is_relative": [true],
        "type": ["image"],
        "measurements": {
          "dimensions": [
            {
              "units": ["pixels"],
              "dimension": ["height"],
              "value": [4008]
            },
            {
              "units": ["pixels"],
              "dimension": ["width"],
              "value": [5344]
            }
          ]
        }
      }
    },
    "manifestURI": ["https://api.fitz.ms/data-distributor/iiif/media-3528641786/manifest"],
    "uvViewerPath": ["https://fitzmuseum.cam.ac.uk/uv.html#?manifest=https://api.fitz.ms/data-distributor/iiif/media-3528641786/manifest&c=0&m=0&cv=0&config=&locales=en-GB:English (GB),cy-GB:Cymraeg,fr-FR:Français (FR),pl-PL:Polski,sv-SE:Svenska&r=0"],
    "uvViewerEmbedHTML": ["<iframe src=\"https://fitzmuseum.cam.ac.uk/uv.html#?manifest=https://api.fitz.ms/data-distributor/iiif/media-3528641786/manifest&c=0&m=0&cv=0&config=&locales=en-GB:English (GB),cy-GB:Cymraeg,fr-FR:Français (FR),pl-PL:Polski,sv-SE:Svenska&r=0\" width=\"560\" height=\"420\" allowfullscreen><\/iframe>"],
    "miradorPath": ["https://data.fitzmuseum.cam.ac.uk/id/image/mirador/media-3528641786"],
    "iiifAPIURI": ["https://data.fitzmuseum.cam.ac.uk/api/v1/iiif/media-3528641786"],
    "type": ["images"]
  },
  "message": ["Retrieved successfully"],
  "httpCode": [200]
}
