{
  "data": {
    "admin": {
      "id": ["media-191519"]
    },
    "apiURI": ["https://data.fitzmuseum.cam.ac.uk/api/v1/images/media-191519"],
    "uri": ["https://data.fitzmuseum.cam.ac.uk/id/image/media-191519"],
    "images": {
      "preview": {
        "resizable": [true],
        "format": ["jpeg"],
        "modified": [1616240486719],
        "location": ["https://data.fitzmuseum.cam.ac.uk/imagestore/cm/cm55/preview_CM_PG_20417_2006_281_29.jpg"],
        "location_is_relative": [true],
        "type": ["image"],
        "measurements": {
          "dimensions": [
            {
              "units": ["pixels"],
              "dimension": ["height"],
              "value": [240]
            },
            {
              "units": ["pixels"],
              "dimension": ["width"],
              "value": [250]
            }
          ]
        }
      },
      "original": {
        "resizable": [true],
        "format": ["jpeg"],
        "modified": [1616240486719],
        "location": ["https://data.fitzmuseum.cam.ac.uk/imagestore/cm/cm55/CM_PG_20417_2006_281_29.jpg"],
        "location_is_relative": [true],
        "type": ["image"],
        "measurements": {
          "dimensions": [
            {
              "units": ["pixels"],
              "dimension": ["height"],
              "value": [346]
            },
            {
              "units": ["pixels"],
              "dimension": ["width"],
              "value": [360]
            }
          ]
        }
      },
      "large": {
        "resizable": [true],
        "format": ["jpeg"],
        "modified": [1616240486719],
        "location": ["https://data.fitzmuseum.cam.ac.uk/imagestore/cm/cm55/CM_PG_20417_2006_281_29.jpg"],
        "location_is_relative": [true],
        "type": ["image"],
        "measurements": {
          "dimensions": [
            {
              "units": ["pixels"],
              "dimension": ["height"],
              "value": [346]
            },
            {
              "units": ["pixels"],
              "dimension": ["width"],
              "value": [360]
            }
          ]
        }
      }
    },
    "type": ["images"]
  },
  "message": ["Retrieved successfully"],
  "httpCode": [200]
}
