{
  "data": {
    "related": [
      {
        "summary_title": ["The Mongols"],
        "admin": {
          "id": ["term-117805"]
        },
        "URI": ["https://data.fitzmuseum.cam.ac.uk/id/terminology/term-117805"],
        "apiURI": ["https://data.fitzmuseum.cam.ac.uk/api/v1/terminology/term-117805"],
        "period": ["term-117805"]
      }
    ],
    "summary_title": ["Mongolia"],
    "name": [
      {
        "value": ["Mongolia"],
        "primary": [true]
      }
    ],
    "admin": {
      "created": [1159488000000],
      "modified": [1159784916000],
      "id": ["term-121508"]
    },
    "type": ["terminology"],
    "URI": ["https://data.fitzmuseum.cam.ac.uk/id/terminology/term-121508"],
    "apiURI": ["https://data.fitzmuseum.cam.ac.uk/api/v1/terminology/term-121508"],
    "term": ["term-121508"]
  },
  "message": ["Retrieved successfully"],
  "httpCode": [200]
}
