{
  "data": {
    "summary": [
      {
        "term": ["term-133132"],
        "URI": ["https://data.fitzmuseum.cam.ac.uk/id/terminology/term-133132"],
        "apiURI": ["https://data.fitzmuseum.cam.ac.uk/api/v1/terminology/term-133132"],
        "summary_title": ["2000 Shillingi"]
      }
    ],
    "institutions": [
      {
        "term": ["agent-149638"],
        "URI": ["https://data.fitzmuseum.cam.ac.uk/id/agent/agent-149638"],
        "apiURI": ["https://data.fitzmuseum.cam.ac.uk/api/v1/agents/agent-149638"],
        "summary_title": ["The Fitzwilliam Museum"]
      }
    ],
    "lifecycle": {
      "acquisition": {
        "method": ["given"],
        "date": [
          {
            "earliest": ["2012"],
            "value": ["2012-01-23"],
            "latest": ["2012"]
          }
        ],
        "agents": {
          "agent": {
            "summary_title": ["Lobel, Richard"],
            "URI": ["https://data.fitzmuseum.cam.ac.uk/id/agent/agent-189517"],
            "apiURI": ["https://data.fitzmuseum.cam.ac.uk/api/v1/agents/agent-189517"],
            "agent": ["agent-189517"]
          }
        }
      },
      "creation": {
        "maker": {
          "maker": {
            "summary_title": ["Coincraft"],
            "URI": ["https://data.fitzmuseum.cam.ac.uk/id/terminology/agent-187083"],
            "apiURI": ["https://data.fitzmuseum.cam.ac.uk/api/v1/agents/agent-187083"],
            "term": ["agent-187083"]
          }
        }
      }
    },
    "identifier": [
      {
        "accession_number": ["CM.446-2012"],
        "type": ["accession number"],
        "value": ["CM.446-2012"],
        "primary": ["1"]
      },
      {
        "priref": ["190891"],
        "type": ["priref"],
        "value": ["190891"]
      },
      {
        "type": ["uri"],
        "uri": ["https://data.fitzmuseum.cam.ac.uk/id/object/190891"],
        "value": ["https://data.fitzmuseum.cam.ac.uk/id/object/190891"]
      }
    ],
    "component": [
      {
        "name": ["Object"],
        "materials": [
          {
            "term": ["term-39581"],
            "URI": ["https://data.fitzmuseum.cam.ac.uk/id/terminology/term-39581"],
            "apiURI": ["https://data.fitzmuseum.cam.ac.uk/api/v1/terminology/term-39581"],
            "summary_title": ["aluminium"]
          }
        ]
      }
    ],
    "multimedia": [
      {
        "preview": {
          "resizable": ["1"],
          "format": ["jpeg"],
          "modified": ["1616251665836"],
          "location": ["https://data.fitzmuseum.cam.ac.uk/imagestore/cm/cm40/preview_CM_446_2012_281_29.jpg"],
          "location_is_relative": ["1"],
          "type": ["image"],
          "measurements": {
            "dimensions": [
              {
                "units": ["pixels"],
                "dimension": ["height"],
                "value": ["249"]
              },
              {
                "units": ["pixels"],
                "dimension": ["width"],
                "value": ["250"]
              }
            ]
          }
        },
        "original": {
          "resizable": ["1"],
          "format": ["jpeg"],
          "modified": ["1616251665836"],
          "location": ["https://data.fitzmuseum.cam.ac.uk/imagestore/cm/cm40/CM_446_2012_281_29.jpg"],
          "location_is_relative": ["1"],
          "type": ["image"],
          "measurements": {
            "dimensions": [
              {
                "units": ["pixels"],
                "dimension": ["height"],
                "value": ["757"]
              },
              {
                "units": ["pixels"],
                "dimension": ["width"],
                "value": ["760"]
              }
            ]
          }
        },
        "large": {
          "resizable": ["1"],
          "format": ["jpeg"],
          "modified": ["1616251665836"],
          "location": ["https://data.fitzmuseum.cam.ac.uk/imagestore/cm/cm40/CM_446_2012_281_29.jpg"],
          "location_is_relative": ["1"],
          "type": ["image"],
          "measurements": {
            "dimensions": [
              {
                "units": ["pixels"],
                "dimension": ["height"],
                "value": ["757"]
              },
              {
                "units": ["pixels"],
                "dimension": ["width"],
                "value": ["760"]
              }
            ]
          }
        },
        "mid": {
          "resizable": ["1"],
          "format": ["jpeg"],
          "modified": ["1616251665836"],
          "location": ["https://data.fitzmuseum.cam.ac.uk/imagestore/cm/cm40/mid_CM_446_2012_281_29.jpg"],
          "location_is_relative": ["1"],
          "type": ["image"],
          "measurements": {
            "dimensions": [
              {
                "units": ["pixels"],
                "dimension": ["height"],
                "value": ["498"]
              },
              {
                "units": ["pixels"],
                "dimension": ["width"],
                "value": ["500"]
              }
            ]
          }
        }
      },
      {
        "preview": {
          "resizable": ["1"],
          "format": ["jpeg"],
          "modified": ["1616244537249"],
          "location": ["https://data.fitzmuseum.cam.ac.uk/imagestore/cm/cm40/preview_CM_446_2012_282_29.jpg"],
          "location_is_relative": ["1"],
          "type": ["image"],
          "measurements": {
            "dimensions": [
              {
                "units": ["pixels"],
                "dimension": ["height"],
                "value": ["248"]
              },
              {
                "units": ["pixels"],
                "dimension": ["width"],
                "value": ["250"]
              }
            ]
          }
        },
        "original": {
          "resizable": ["1"],
          "format": ["jpeg"],
          "modified": ["1616244537249"],
          "location": ["https://data.fitzmuseum.cam.ac.uk/imagestore/cm/cm40/CM_446_2012_282_29.jpg"],
          "location_is_relative": ["1"],
          "type": ["image"],
          "measurements": {
            "dimensions": [
              {
                "units": ["pixels"],
                "dimension": ["height"],
                "value": ["755"]
              },
              {
                "units": ["pixels"],
                "dimension": ["width"],
                "value": ["760"]
              }
            ]
          }
        },
        "large": {
          "resizable": ["1"],
          "format": ["jpeg"],
          "modified": ["1616244537249"],
          "location": ["https://data.fitzmuseum.cam.ac.uk/imagestore/cm/cm40/CM_446_2012_282_29.jpg"],
          "location_is_relative": ["1"],
          "type": ["image"],
          "measurements": {
            "dimensions": [
              {
                "units": ["pixels"],
                "dimension": ["height"],
                "value": ["755"]
              },
              {
                "units": ["pixels"],
                "dimension": ["width"],
                "value": ["760"]
              }
            ]
          }
        },
        "mid": {
          "resizable": ["1"],
          "format": ["jpeg"],
          "modified": ["1616244537249"],
          "location": ["https://data.fitzmuseum.cam.ac.uk/imagestore/cm/cm40/mid_CM_446_2012_282_29.jpg"],
          "location_is_relative": ["1"],
          "type": ["image"],
          "measurements": {
            "dimensions": [
              {
                "units": ["pixels"],
                "dimension": ["height"],
                "value": ["497"]
              },
              {
                "units": ["pixels"],
                "dimension": ["width"],
                "value": ["500"]
              }
            ]
          }
        }
      }
    ],
    "name": [
      {
        "term": ["term-133132"],
        "URI": ["https://data.fitzmuseum.cam.ac.uk/id/terminology/term-133132"],
        "apiURI": ["https://data.fitzmuseum.cam.ac.uk/api/v1/terminology/term-133132"],
        "summary_title": ["2000 Shillingi"]
      },
      {
        "term": ["term-133131"],
        "URI": ["https://data.fitzmuseum.cam.ac.uk/id/terminology/term-133131"],
        "apiURI": ["https://data.fitzmuseum.cam.ac.uk/api/v1/terminology/term-133131"],
        "summary_title": ["Olympics - Atlanta"]
      },
      {
        "term": ["term-16252"],
        "URI": ["https://data.fitzmuseum.cam.ac.uk/id/terminology/term-16252"],
        "apiURI": ["https://data.fitzmuseum.cam.ac.uk/api/v1/terminology/term-16252"],
        "summary_title": ["Tanzania"]
      },
      {
        "term": ["term-131220"],
        "URI": ["https://data.fitzmuseum.cam.ac.uk/id/terminology/term-131220"],
        "apiURI": ["https://data.fitzmuseum.cam.ac.uk/api/v1/terminology/term-131220"],
        "summary_title": ["pattern"]
      }
    ],
    "admin": {
      "created": ["1358240555000"],
      "modified": ["1358240624000"],
      "id": ["object-190891"]
    },
    "inscription": [
      {
        "transcription": [
          {
            "value": ["TANZANIA 35th ANNIVERSARY OF INDEPENDENCE 1961-2019"]
          }
        ],
        "description": [
          {
            "value": ["Tanzanian Coat of Arms"]
          }
        ],
        "location": ["obverse"],
        "type": ["design"]
      },
      {
        "transcription": [
          {
            "value": ["ATLANTA GEORGIA U.S.A. 1996 OLYMPICS CENTENARY 1896-1996 / XXVI OLYMPIAD"]
          }
        ],
        "description": [
          {
            "value": ["Judoka and Olympic torch"]
          }
        ],
        "location": ["reverse"],
        "type": ["design"]
      }
    ],
    "owners": [
      {
        "URI": ["https://data.fitzmuseum.cam.ac.uk/id/agent/agent-149638"],
        "apiURI": ["https://data.fitzmuseum.cam.ac.uk/api/v1/agents/agent-149638"],
        "owner": ["agent-149638"],
        "summary_title": ["The Fitzwilliam Museum"]
      }
    ],
    "categories": [
      {
        "term": ["term-100804"],
        "URI": ["https://data.fitzmuseum.cam.ac.uk/id/terminology/term-100804"],
        "apiURI": ["https://data.fitzmuseum.cam.ac.uk/api/v1/terminology/term-100804"],
        "summary_title": ["coin"]
      }
    ],
    "department": {
      "value": ["Coins and Medals"]
    },
    "type": ["objects"],
    "apiURI": ["https://data.fitzmuseum.cam.ac.uk/api/v1/objects/object-190891"],
    "URI": ["https://data.fitzmuseum.cam.ac.uk/id/object/190891"],
    "object": ["object-190891"]
  },
  "message": ["Retrieved successfully"],
  "httpCode": [200]
}
