{
  "data": {
    "summary": [
      {
        "term": ["term-108938"],
        "URI": ["https://data.fitzmuseum.cam.ac.uk/id/terminology/term-108938"],
        "apiURI": ["https://data.fitzmuseum.cam.ac.uk/api/v1/terminology/term-108938"],
        "summary_title": ["collar"]
      }
    ],
    "identifier": [
      {
        "accession_number": ["T.4-1981"],
        "type": ["accession number"],
        "value": ["T.4-1981"],
        "primary": ["1"]
      },
      {
        "priref": ["110154"],
        "type": ["priref"],
        "value": ["110154"]
      },
      {
        "type": ["uri"],
        "uri": ["https://data.fitzmuseum.cam.ac.uk/id/object/110154"],
        "value": ["https://data.fitzmuseum.cam.ac.uk/id/object/110154"]
      }
    ],
    "admin": {
      "created": ["1312637261000"],
      "modified": ["1507562160000"],
      "id": ["object-110154"]
    },
    "description": [
      {
        "value": ["Collar, cotton, machine made 3-twist net decorated with tambour work."]
      }
    ],
    "owners": [
      {
        "URI": ["https://data.fitzmuseum.cam.ac.uk/id/agent/agent-149638"],
        "apiURI": ["https://data.fitzmuseum.cam.ac.uk/api/v1/agents/agent-149638"],
        "owner": ["agent-149638"],
        "summary_title": ["The Fitzwilliam Museum"]
      }
    ],
    "institutions": [
      {
        "term": ["agent-149638"],
        "URI": ["https://data.fitzmuseum.cam.ac.uk/id/agent/agent-149638"],
        "apiURI": ["https://data.fitzmuseum.cam.ac.uk/api/v1/agents/agent-149638"],
        "summary_title": ["The Fitzwilliam Museum"]
      }
    ],
    "lifecycle": {
      "acquisition": {
        "method": ["given"],
        "date": [
          {
            "earliest": ["1981"],
            "value": ["1981-02-02"],
            "latest": ["1981"]
          }
        ],
        "agents": {
          "agent": {
            "summary_title": ["Croucher, Helen, Miss"],
            "URI": ["https://data.fitzmuseum.cam.ac.uk/id/agent/agent-169185"],
            "apiURI": ["https://data.fitzmuseum.cam.ac.uk/api/v1/agents/agent-169185"],
            "agent": ["agent-169185"]
          }
        }
      },
      "creation": {
        "date": [
          {
            "range": ["1"],
            "from": {
              "era": [
                ["CE"]
              ],
              "precision": ["circa"],
              "earliest": ["1870"],
              "value": ["1870"],
              "latest": ["1870"]
            },
            "to": {
              "era": [
                ["CE"]
              ],
              "precision": ["circa"],
              "earliest": ["1899"],
              "value": ["1899"],
              "latest": ["1899"]
            },
            "earliest": ["1870"],
            "latest": ["1899"]
          }
        ],
        "periods": [
          {
            "summary_title": ["late 19th Century"],
            "period": ["term-108070"],
            "apiURI": ["https://data.fitzmuseum.cam.ac.uk/api/v1/periods/term-108070"],
            "URI": ["https://data.fitzmuseum.cam.ac.uk/id/terminology/term-108070"]
          }
        ],
        "maker": {
          "maker": {
            "summary_title": ["Unknown"],
            "URI": ["https://data.fitzmuseum.cam.ac.uk/id/terminology/agent-149652"],
            "apiURI": ["https://data.fitzmuseum.cam.ac.uk/api/v1/agents/agent-149652"],
            "term": ["agent-149652"]
          }
        },
        "places": [
          {
            "summary_title": ["Coggeshall"],
            "apiURI": ["https://data.fitzmuseum.cam.ac.uk/api/v1/places/term-118696"],
            "URI": ["https://data.fitzmuseum.cam.ac.uk/id/terminology/term-118696"],
            "place": ["term-118696"],
            "coordinates": {
              "lat": ["51.8818632"],
              "lng": ["0.68187469042475"]
            },
            "hierarchies": [
              {
                "summary_title": ["England"],
                "type": ["country"]
              }
            ]
          },
          {
            "summary_title": ["Limerick"],
            "apiURI": ["https://data.fitzmuseum.cam.ac.uk/api/v1/places/term-118695"],
            "URI": ["https://data.fitzmuseum.cam.ac.uk/id/terminology/term-118695"],
            "place": ["term-118695"],
            "coordinates": {
              "lat": ["52.661252"],
              "lng": ["-8.6301239"]
            },
            "hierarchies": [
              {
                "summary_title": ["Ireland"],
                "type": ["country"]
              }
            ]
          }
        ]
      }
    },
    "component": [
      {
        "name": ["Max."],
        "materials": []
      }
    ],
    "techniques": [
      {
        "term": ["term-118668"],
        "URI": ["https://data.fitzmuseum.cam.ac.uk/id/terminology/term-118668"],
        "apiURI": ["https://data.fitzmuseum.cam.ac.uk/api/v1/terminology/term-118668"],
        "summary_title": ["machine made net"],
        "descriptions": [
          {
            "description": ["cotton, machine made 3-twist net decorated with tambour work."]
          }
        ]
      },
      {
        "term": ["term-118694"],
        "URI": ["https://data.fitzmuseum.cam.ac.uk/id/terminology/term-118694"],
        "apiURI": ["https://data.fitzmuseum.cam.ac.uk/api/v1/terminology/term-118694"],
        "summary_title": ["tambour work"],
        "descriptions": []
      }
    ],
    "name": [
      {
        "term": ["term-108938"],
        "URI": ["https://data.fitzmuseum.cam.ac.uk/id/terminology/term-108938"],
        "apiURI": ["https://data.fitzmuseum.cam.ac.uk/api/v1/terminology/term-108938"],
        "summary_title": ["collar"]
      },
      {
        "term": ["term-118668"],
        "URI": ["https://data.fitzmuseum.cam.ac.uk/id/terminology/term-118668"],
        "apiURI": ["https://data.fitzmuseum.cam.ac.uk/api/v1/terminology/term-118668"],
        "summary_title": ["machine made net"]
      },
      {
        "term": ["term-118694"],
        "URI": ["https://data.fitzmuseum.cam.ac.uk/id/terminology/term-118694"],
        "apiURI": ["https://data.fitzmuseum.cam.ac.uk/api/v1/terminology/term-118694"],
        "summary_title": ["tambour work"]
      }
    ],
    "categories": [
      {
        "term": ["term-39352"],
        "URI": ["https://data.fitzmuseum.cam.ac.uk/id/terminology/term-39352"],
        "apiURI": ["https://data.fitzmuseum.cam.ac.uk/api/v1/terminology/term-39352"],
        "summary_title": ["lace"]
      }
    ],
    "department": {
      "value": ["Applied Arts"]
    },
    "measurements": {
      "dimensions": [
        {
          "units": ["cm"],
          "dimension": ["Width"],
          "value": ["22.5"]
        }
      ]
    },
    "publications": [
      {
        "term": ["publication-4903"],
        "URI": ["https://data.fitzmuseum.cam.ac.uk/id/publication/publication-4903"],
        "apiURI": ["https://data.fitzmuseum.cam.ac.uk/api/v1/publications/publication-4903"],
        "summary_title": ["Lace"],
        "page": ["8"]
      }
    ],
    "type": ["objects"],
    "apiURI": ["https://data.fitzmuseum.cam.ac.uk/api/v1/objects/object-110154"],
    "URI": ["https://data.fitzmuseum.cam.ac.uk/id/object/110154"],
    "object": ["object-110154"]
  },
  "message": ["Retrieved successfully"],
  "httpCode": [200]
}
