{
  "data": {
    "summary": [
      {
        "term": ["term-130631"],
        "URI": ["https://data.fitzmuseum.cam.ac.uk/id/terminology/term-130631"],
        "apiURI": ["https://data.fitzmuseum.cam.ac.uk/api/v1/terminology/term-130631"],
        "summary_title": ["Fishing Weight"]
      }
    ],
    "identifier": [
      {
        "accession_number": ["CM.1896-2008"],
        "type": ["accession number"],
        "value": ["CM.1896-2008"],
        "primary": ["1"]
      },
      {
        "priref": ["184003"],
        "type": ["priref"],
        "value": ["184003"]
      },
      {
        "type": ["uri"],
        "uri": ["https://data.fitzmuseum.cam.ac.uk/id/object/184003"],
        "value": ["https://data.fitzmuseum.cam.ac.uk/id/object/184003"]
      }
    ],
    "note": [
      {
        "type": ["history note"],
        "value": ["Bought as a part of a group for £100"]
      }
    ],
    "admin": {
      "created": ["1312637261000"],
      "modified": ["1431942759000"],
      "id": ["object-184003"]
    },
    "description": [
      {
        "value": ["A cylindrical lead fishing weight with ovoid central hole. Join mark is evident and lead is very thin here."]
      }
    ],
    "owners": [
      {
        "URI": ["https://data.fitzmuseum.cam.ac.uk/id/agent/agent-149638"],
        "apiURI": ["https://data.fitzmuseum.cam.ac.uk/api/v1/agents/agent-149638"],
        "owner": ["agent-149638"],
        "summary_title": ["The Fitzwilliam Museum"]
      }
    ],
    "institutions": [
      {
        "term": ["agent-149638"],
        "URI": ["https://data.fitzmuseum.cam.ac.uk/id/agent/agent-149638"],
        "apiURI": ["https://data.fitzmuseum.cam.ac.uk/api/v1/agents/agent-149638"],
        "summary_title": ["The Fitzwilliam Museum"]
      }
    ],
    "lifecycle": {
      "acquisition": {
        "method": ["bought"],
        "date": [
          {
            "earliest": ["2008"],
            "value": ["2008-11-24"],
            "latest": ["2008"]
          }
        ],
        "agents": {
          "agent": {
            "summary_title": ["Taylor, Geoffrey"],
            "URI": ["https://data.fitzmuseum.cam.ac.uk/id/agent/agent-151969"],
            "apiURI": ["https://data.fitzmuseum.cam.ac.uk/api/v1/agents/agent-151969"],
            "agent": ["agent-151969"]
          }
        }
      },
      "collection": {
        "places": [
          {
            "summary_title": ["Torksey, Lincolnshire"],
            "apiURI": ["https://data.fitzmuseum.cam.ac.uk/api/v1/places/term-130593"],
            "URI": ["https://data.fitzmuseum.cam.ac.uk/id/terminology/term-130593"],
            "coordinates": {
              "lat": ["53.3002756"],
              "lng": ["-0.7448882"]
            }
          }
        ]
      },
      "creation": {
        "date": [
          {
            "range": ["1"],
            "from": {
              "earliest": ["500"],
              "value": ["500"],
              "latest": ["500"]
            },
            "to": {
              "earliest": ["1499"],
              "value": ["1499"],
              "latest": ["1499"]
            },
            "earliest": ["500"],
            "latest": ["1499"]
          }
        ],
        "periods": [
          {
            "summary_title": ["Medieval"],
            "period": ["term-10603"],
            "apiURI": ["https://data.fitzmuseum.cam.ac.uk/api/v1/periods/term-10603"],
            "URI": ["https://data.fitzmuseum.cam.ac.uk/id/terminology/term-10603"]
          }
        ]
      }
    },
    "component": [
      {
        "name": ["Object"],
        "materials": [
          {
            "term": ["term-39596"],
            "URI": ["https://data.fitzmuseum.cam.ac.uk/id/terminology/term-39596"],
            "apiURI": ["https://data.fitzmuseum.cam.ac.uk/api/v1/terminology/term-39596"],
            "summary_title": ["lead"]
          }
        ]
      },
      {
        "name": ["Maximum Diameter Of Central Hole"],
        "materials": []
      },
      {
        "name": ["Whole Object"],
        "materials": []
      }
    ],
    "multimedia": [
      {
        "preview": {
          "resizable": ["1"],
          "format": ["jpeg"],
          "modified": ["1616243914377"],
          "location": ["https://data.fitzmuseum.cam.ac.uk/imagestore/cm/cm34/preview_CM_1896_2008_281_29.jpg"],
          "location_is_relative": ["1"],
          "type": ["image"],
          "measurements": {
            "dimensions": [
              {
                "units": ["pixels"],
                "dimension": ["height"],
                "value": ["236"]
              },
              {
                "units": ["pixels"],
                "dimension": ["width"],
                "value": ["250"]
              }
            ]
          }
        },
        "original": {
          "resizable": ["1"],
          "format": ["jpeg"],
          "modified": ["1616243914377"],
          "location": ["https://data.fitzmuseum.cam.ac.uk/imagestore/cm/cm34/CM_1896_2008_281_29.jpg"],
          "location_is_relative": ["1"],
          "type": ["image"],
          "measurements": {
            "dimensions": [
              {
                "units": ["pixels"],
                "dimension": ["height"],
                "value": ["718"]
              },
              {
                "units": ["pixels"],
                "dimension": ["width"],
                "value": ["760"]
              }
            ]
          }
        },
        "large": {
          "resizable": ["1"],
          "format": ["jpeg"],
          "modified": ["1616243914377"],
          "location": ["https://data.fitzmuseum.cam.ac.uk/imagestore/cm/cm34/CM_1896_2008_281_29.jpg"],
          "location_is_relative": ["1"],
          "type": ["image"],
          "measurements": {
            "dimensions": [
              {
                "units": ["pixels"],
                "dimension": ["height"],
                "value": ["718"]
              },
              {
                "units": ["pixels"],
                "dimension": ["width"],
                "value": ["760"]
              }
            ]
          }
        },
        "mid": {
          "resizable": ["1"],
          "format": ["jpeg"],
          "modified": ["1616243914377"],
          "location": ["https://data.fitzmuseum.cam.ac.uk/imagestore/cm/cm34/mid_CM_1896_2008_281_29.jpg"],
          "location_is_relative": ["1"],
          "type": ["image"],
          "measurements": {
            "dimensions": [
              {
                "units": ["pixels"],
                "dimension": ["height"],
                "value": ["472"]
              },
              {
                "units": ["pixels"],
                "dimension": ["width"],
                "value": ["500"]
              }
            ]
          }
        }
      },
      {
        "preview": {
          "resizable": ["1"],
          "format": ["jpeg"],
          "modified": ["1616256498284"],
          "location": ["https://data.fitzmuseum.cam.ac.uk/imagestore/cm/cm34/preview_CM_1896_2008_282_29.jpg"],
          "location_is_relative": ["1"],
          "type": ["image"],
          "measurements": {
            "dimensions": [
              {
                "units": ["pixels"],
                "dimension": ["height"],
                "value": ["242"]
              },
              {
                "units": ["pixels"],
                "dimension": ["width"],
                "value": ["250"]
              }
            ]
          }
        },
        "original": {
          "resizable": ["1"],
          "format": ["jpeg"],
          "modified": ["1616256498284"],
          "location": ["https://data.fitzmuseum.cam.ac.uk/imagestore/cm/cm34/CM_1896_2008_282_29.jpg"],
          "location_is_relative": ["1"],
          "type": ["image"],
          "measurements": {
            "dimensions": [
              {
                "units": ["pixels"],
                "dimension": ["height"],
                "value": ["737"]
              },
              {
                "units": ["pixels"],
                "dimension": ["width"],
                "value": ["760"]
              }
            ]
          }
        },
        "large": {
          "resizable": ["1"],
          "format": ["jpeg"],
          "modified": ["1616256498284"],
          "location": ["https://data.fitzmuseum.cam.ac.uk/imagestore/cm/cm34/CM_1896_2008_282_29.jpg"],
          "location_is_relative": ["1"],
          "type": ["image"],
          "measurements": {
            "dimensions": [
              {
                "units": ["pixels"],
                "dimension": ["height"],
                "value": ["737"]
              },
              {
                "units": ["pixels"],
                "dimension": ["width"],
                "value": ["760"]
              }
            ]
          }
        },
        "mid": {
          "resizable": ["1"],
          "format": ["jpeg"],
          "modified": ["1616256498284"],
          "location": ["https://data.fitzmuseum.cam.ac.uk/imagestore/cm/cm34/mid_CM_1896_2008_282_29.jpg"],
          "location_is_relative": ["1"],
          "type": ["image"],
          "measurements": {
            "dimensions": [
              {
                "units": ["pixels"],
                "dimension": ["height"],
                "value": ["485"]
              },
              {
                "units": ["pixels"],
                "dimension": ["width"],
                "value": ["500"]
              }
            ]
          }
        }
      },
      {
        "preview": {
          "resizable": ["1"],
          "format": ["jpeg"],
          "modified": ["1616273919829"],
          "location": ["https://data.fitzmuseum.cam.ac.uk/imagestore/cm/cm34/preview_CM_1896_2008_283_29.jpg"],
          "location_is_relative": ["1"],
          "type": ["image"],
          "measurements": {
            "dimensions": [
              {
                "units": ["pixels"],
                "dimension": ["height"],
                "value": ["283"]
              },
              {
                "units": ["pixels"],
                "dimension": ["width"],
                "value": ["250"]
              }
            ]
          }
        },
        "original": {
          "resizable": ["1"],
          "format": ["jpeg"],
          "modified": ["1616273919829"],
          "location": ["https://data.fitzmuseum.cam.ac.uk/imagestore/cm/cm34/CM_1896_2008_283_29.jpg"],
          "location_is_relative": ["1"],
          "type": ["image"],
          "measurements": {
            "dimensions": [
              {
                "units": ["pixels"],
                "dimension": ["height"],
                "value": ["765"]
              },
              {
                "units": ["pixels"],
                "dimension": ["width"],
                "value": ["676"]
              }
            ]
          }
        },
        "large": {
          "resizable": ["1"],
          "format": ["jpeg"],
          "modified": ["1616273919829"],
          "location": ["https://data.fitzmuseum.cam.ac.uk/imagestore/cm/cm34/CM_1896_2008_283_29.jpg"],
          "location_is_relative": ["1"],
          "type": ["image"],
          "measurements": {
            "dimensions": [
              {
                "units": ["pixels"],
                "dimension": ["height"],
                "value": ["765"]
              },
              {
                "units": ["pixels"],
                "dimension": ["width"],
                "value": ["676"]
              }
            ]
          }
        },
        "mid": {
          "resizable": ["1"],
          "format": ["jpeg"],
          "modified": ["1616273919829"],
          "location": ["https://data.fitzmuseum.cam.ac.uk/imagestore/cm/cm34/mid_CM_1896_2008_283_29.jpg"],
          "location_is_relative": ["1"],
          "type": ["image"],
          "measurements": {
            "dimensions": [
              {
                "units": ["pixels"],
                "dimension": ["height"],
                "value": ["566"]
              },
              {
                "units": ["pixels"],
                "dimension": ["width"],
                "value": ["500"]
              }
            ]
          }
        }
      }
    ],
    "name": [
      {
        "term": ["term-130631"],
        "URI": ["https://data.fitzmuseum.cam.ac.uk/id/terminology/term-130631"],
        "apiURI": ["https://data.fitzmuseum.cam.ac.uk/api/v1/terminology/term-130631"],
        "summary_title": ["Fishing Weight"]
      }
    ],
    "department": {
      "value": ["Coins and Medals"]
    },
    "measurements": {
      "dimensions": [
        {
          "units": ["mm"],
          "dimension": ["Height"],
          "value": ["22"]
        }
      ]
    },
    "publications": [
      {
        "term": ["publication-200002752"],
        "URI": ["https://data.fitzmuseum.cam.ac.uk/id/publication/publication-200002752"],
        "apiURI": ["https://data.fitzmuseum.cam.ac.uk/api/v1/publications/publication-200002752"],
        "summary_title": ["A Medieval Fishery on Whittlesea Mere, Cambridgeshire"]
      }
    ],
    "type": ["objects"],
    "apiURI": ["https://data.fitzmuseum.cam.ac.uk/api/v1/objects/object-184003"],
    "URI": ["https://data.fitzmuseum.cam.ac.uk/id/object/184003"],
    "object": ["object-184003"]
  },
  "message": ["Retrieved successfully"],
  "httpCode": [200]
}
