{
  "data": {
    "related": [
      {
        "@link": {
          "type": ["reference"]
        },
        "summary_title": ["military history"],
        "admin": {
          "uid": ["adlib-term-23456"],
          "id": ["term-23456"],
          "uuid": ["b7cd7312-3735-3364-8c9e-bba5fef9dd24"]
        }
      }
    ],
    "summary_title": ["wars"],
    "name": [
      {
        "value": ["wars"],
        "primary": [true]
      }
    ],
    "type": ["terminology"],
    "URI": ["https://data.fitzmuseum.cam.ac.uk/id/terminology/term-25147"],
    "apiURI": ["https://data.fitzmuseum.cam.ac.uk/api/v1/terminology/term-25147"],
    "term": ["term-25147"]
  },
  "message": ["Retrieved successfully"],
  "httpCode": [200]
}
