{
  "data": {
    "summary_title": ["Bäriswil"],
    "name": [
      {
        "value": ["Bäriswil"],
        "primary": [true]
      }
    ],
    "admin": {
      "created": [1312636083000],
      "modified": [1448361372000],
      "id": ["term-116917"]
    },
    "type": ["terminology"],
    "URI": ["https://data.fitzmuseum.cam.ac.uk/id/terminology/term-116917"],
    "apiURI": ["https://data.fitzmuseum.cam.ac.uk/api/v1/terminology/term-116917"],
    "term": ["term-116917"]
  },
  "message": ["Retrieved successfully"],
  "httpCode": [200]
}
