{
  "data": {
    "summary_title": ["Tenos"],
    "name": [
      {
        "value": ["Tenos"],
        "primary": [true]
      }
    ],
    "admin": {
      "created": [1207008000000],
      "modified": [1337264173000],
      "id": ["term-126613"]
    },
    "type": ["terminology"],
    "URI": ["https://data.fitzmuseum.cam.ac.uk/id/terminology/term-126613"],
    "apiURI": ["https://data.fitzmuseum.cam.ac.uk/api/v1/terminology/term-126613"],
    "term": ["term-126613"]
  },
  "message": ["Retrieved successfully"],
  "httpCode": [200]
}
