{
  "data": {
    "summary_title": ["miniature gardens"],
    "name": [
      {
        "value": ["miniature gardens"],
        "primary": [true]
      }
    ],
    "admin": {
      "created": [1312632483000],
      "modified": [1312632562000],
      "id": ["term-66830"]
    },
    "type": ["terminology"],
    "URI": ["https://data.fitzmuseum.cam.ac.uk/id/terminology/term-66830"],
    "apiURI": ["https://data.fitzmuseum.cam.ac.uk/api/v1/terminology/term-66830"],
    "term": ["term-66830"]
  },
  "message": ["Retrieved successfully"],
  "httpCode": [200]
}
