{
  "data": {
    "summary_title": ["methylene oxide"],
    "name": [
      {
        "value": ["methylene oxide"],
        "primary": [true]
      }
    ],
    "admin": {
      "created": [1312632483000],
      "modified": [1312632521000],
      "id": ["term-30407"]
    },
    "type": ["terminology"],
    "URI": ["https://data.fitzmuseum.cam.ac.uk/id/terminology/term-30407"],
    "apiURI": ["https://data.fitzmuseum.cam.ac.uk/api/v1/terminology/term-30407"],
    "term": ["term-30407"]
  },
  "message": ["Retrieved successfully"],
  "httpCode": [200]
}
