{
  "data": {
    "related": [
      {
        "@link": {
          "type": ["reference"]
        },
        "summary_title": ["puppetry (performing arts)"],
        "admin": {
          "uid": ["adlib-term-23603"],
          "id": ["term-23603"],
          "uuid": ["4a6fbe64-bd9c-3e82-813e-54a7e7eaccba"]
        }
      }
    ],
    "summary_title": ["puppet theaters"],
    "name": [
      {
        "value": ["puppet theaters"],
        "primary": [true]
      }
    ],
    "type": ["terminology"],
    "URI": ["https://data.fitzmuseum.cam.ac.uk/id/terminology/term-60833"],
    "apiURI": ["https://data.fitzmuseum.cam.ac.uk/api/v1/terminology/term-60833"],
    "term": ["term-60833"]
  },
  "message": ["Retrieved successfully"],
  "httpCode": [200]
}
